<?xml version="1.0" standalone="yes"?>
<MpDataSet>
  <MenuTree>239</MenuTree>
  <MpStyle>Style1</MpStyle>
  <DataSet>
    <DataLable>BlockA</DataLable>
    <DataRemark>諸事大吉</DataRemark>
    <DataNode>3406</DataNode>
    <SqlCondition />
    <SqlOrderBy />
    <SqlTop />
    <WithContent>N</WithContent>
    <ContentData>N</ContentData>
    <ContentLength />
    <IsTitle>Y</IsTitle>
    <IsPic>Y</IsPic>
    <IsPostDate>N</IsPostDate>
    <IsExcerpt>N</IsExcerpt>
    <ShowStyle>Style3</ShowStyle>
    <mpShow>Y</mpShow>
  </DataSet>
  <DataSet>
    <DataLable>BlockB</DataLable>
    <DataRemark>豬頭諸腦</DataRemark>
    <DataNode>3406</DataNode>
    <SqlCondition />
    <SqlOrderBy />
    <SqlTop />
    <WithContent>N</WithContent>
    <ContentData>N</ContentData>
    <ContentLength />
    <IsTitle>Y</IsTitle>
    <IsPic>Y</IsPic>
    <IsPostDate>N</IsPostDate>
    <IsExcerpt>N</IsExcerpt>
    <ShowStyle>Style1</ShowStyle>
    <mpShow>Y</mpShow>
  </DataSet>
  <DataSet>
    <DataLable>BlockC</DataLable>
    <DataRemark />
    <DataNode>3406</DataNode>
    <SqlCondition />
    <SqlOrderBy />
    <SqlTop />
    <WithContent>N</WithContent>
    <ContentData>N</ContentData>
    <ContentLength />
    <IsTitle>Y</IsTitle>
    <IsPic>N</IsPic>
    <IsPostDate>N</IsPostDate>
    <IsExcerpt>N</IsExcerpt>
    <ShowStyle>Style1</ShowStyle>
    <mpShow>Y</mpShow>
  </DataSet>
  <DataSet>
    <DataLable>BlockD</DataLable>
    <DataRemark />
    <DataNode>0</DataNode>
    <SqlCondition />
    <SqlOrderBy />
    <SqlTop />
    <WithContent>N</WithContent>
    <ContentData>N</ContentData>
    <ContentLength />
    <IsTitle>Y</IsTitle>
    <IsPic>N</IsPic>
    <IsPostDate>N</IsPostDate>
    <IsExcerpt>N</IsExcerpt>
    <ShowStyle>Style1</ShowStyle>
    <mpShow>Y</mpShow>
  </DataSet>
  <DataSet>
    <DataLable>BlockE</DataLable>
    <DataRemark />
    <DataNode>0</DataNode>
    <SqlCondition />
    <SqlOrderBy />
    <SqlTop />
    <WithContent>N</WithContent>
    <ContentData>N</ContentData>
    <ContentLength />
    <IsTitle>Y</IsTitle>
    <IsPic>N</IsPic>
    <IsPostDate>N</IsPostDate>
    <IsExcerpt>N</IsExcerpt>
    <ShowStyle>Style1</ShowStyle>
    <mpShow>Y</mpShow>
  </DataSet>
</MpDataSet>