<?xml version="1.0"  encoding="utf-8" ?>
<DataSchemaDef>
	<dsTable>
		<tableName>InfoUser</tableName>
		<tableDesc>使用者</tableDesc>
		<fieldList>
			<field>
				<fieldName>UserID</fieldName>
				<fieldLabel>UserID</fieldLabel>
				<dataType>varchar</dataType>
				<dataLen>10</dataLen>
				<inputLen>10</inputLen>
				<canNull>N</canNull>
				<isPrimaryKey>Y</isPrimaryKey>
				<identity>N</identity>
				<inputType>textbox</inputType>
				<fieldDesc></fieldDesc>
				<refLookup></refLookup>
				<rows></rows>
				<cols></cols>
			</field>
			<field>
				<fieldName>Password</fieldName>
				<fieldLabel>Password</fieldLabel>
				<dataType>varchar</dataType>
				<dataLen>10</dataLen>
				<inputLen>10</inputLen>
				<canNull>N</canNull>
				<isPrimaryKey>N</isPrimaryKey>
				<identity>N</identity>
				<inputType>textbox</inputType>
				<fieldDesc></fieldDesc>
				<refLookup></refLookup>
				<rows></rows>
				<cols></cols>
			</field>
			<field>
				<fieldName>UserName</fieldName>
				<fieldLabel>UserName</fieldLabel>
				<dataType>varchar</dataType>
				<dataLen>20</dataLen>
				<inputLen>10</inputLen>
				<canNull>N</canNull>
				<isPrimaryKey>N</isPrimaryKey>
				<identity>N</identity>
				<inputType>textbox</inputType>
				<fieldDesc></fieldDesc>
				<refLookup></refLookup>
				<rows></rows>
				<cols></cols>
			</field>
			<field>
				<fieldName>UserType</fieldName>
				<fieldLabel>UserType</fieldLabel>
				<dataType>varchar</dataType>
				<dataLen>1</dataLen>
				<inputLen>10</inputLen>
				<canNull>N</canNull>
				<isPrimaryKey>N</isPrimaryKey>
				<identity>N</identity>
				<inputType>textbox</inputType>
				<fieldDesc></fieldDesc>
				<refLookup></refLookup>
				<rows></rows>
				<cols></cols>
			</field>
			<field>
				<fieldName>deptID</fieldName>
				<fieldLabel>deptID</fieldLabel>
				<dataType>varchar</dataType>
				<dataLen>10</dataLen>
				<inputLen>10</inputLen>
				<canNull>Y</canNull>
				<isPrimaryKey>N</isPrimaryKey>
				<identity>N</identity>
				<inputType>textbox</inputType>
				<fieldDesc></fieldDesc>
				<refLookup></refLookup>
				<rows></rows>
				<cols></cols>
			</field>
			<field>
				<fieldName>jobName</fieldName>
				<fieldLabel>jobName</fieldLabel>
				<dataType>varchar</dataType>
				<dataLen>30</dataLen>
				<inputLen>10</inputLen>
				<canNull>Y</canNull>
				<isPrimaryKey>N</isPrimaryKey>
				<identity>N</identity>
				<inputType>textbox</inputType>
				<fieldDesc></fieldDesc>
				<refLookup></refLookup>
				<rows></rows>
				<cols></cols>
			</field>
			<field>
				<fieldName>Email</fieldName>
				<fieldLabel>Email</fieldLabel>
				<dataType>varchar</dataType>
				<dataLen>50</dataLen>
				<inputLen>10</inputLen>
				<canNull>Y</canNull>
				<isPrimaryKey>N</isPrimaryKey>
				<identity>N</identity>
				<inputType>textbox</inputType>
				<fieldDesc></fieldDesc>
				<refLookup></refLookup>
				<rows></rows>
				<cols></cols>
			</field>
			<field>
				<fieldName>ugrpID</fieldName>
				<fieldLabel>ugrpID</fieldLabel>
				<dataType>varchar</dataType>
				<dataLen>200</dataLen>
				<inputLen>10</inputLen>
				<canNull>N</canNull>
				<isPrimaryKey>N</isPrimaryKey>
				<identity>N</identity>
				<inputType>textbox</inputType>
				<fieldDesc></fieldDesc>
				<refLookup></refLookup>
				<rows></rows>
				<cols></cols>
			</field>
			<field>
				<fieldName>LastVisit</fieldName>
				<fieldLabel>LastVisit</fieldLabel>
				<dataType>smalldatetime</dataType>
				<dataLen>16</dataLen>
				<inputLen>10</inputLen>
				<canNull>Y</canNull>
				<isPrimaryKey>N</isPrimaryKey>
				<identity>N</identity>
				<inputType>textbox</inputType>
				<fieldDesc></fieldDesc>
				<refLookup></refLookup>
				<rows></rows>
				<cols></cols>
			</field>
			<field>
				<fieldName>VisitCount</fieldName>
				<fieldLabel>VisitCount</fieldLabel>
				<dataType>smallint</dataType>
				<dataLen>2</dataLen>
				<inputLen>10</inputLen>
				<canNull>N</canNull>
				<isPrimaryKey>N</isPrimaryKey>
				<identity>N</identity>
				<inputType>textbox</inputType>
				<fieldDesc></fieldDesc>
				<refLookup></refLookup>
				<rows></rows>
				<cols></cols>
			</field>
			<field>
				<fieldName>ugrpName</fieldName>
				<fieldLabel>ugrpName</fieldLabel>
				<dataType>char</dataType>
				<dataLen>500</dataLen>
				<inputLen>10</inputLen>
				<canNull>Y</canNull>
				<isPrimaryKey>N</isPrimaryKey>
				<identity>N</identity>
				<inputType>textbox</inputType>
				<fieldDesc></fieldDesc>
				<refLookup></refLookup>
				<rows></rows>
				<cols></cols>
			</field>
			<field>
				<fieldName>Telephone</fieldName>
				<fieldLabel>電話</fieldLabel>
				<dataType>varchar</dataType>
				<dataLen>30</dataLen>
				<inputLen>30</inputLen>
				<canNull>Y</canNull>
				<isPrimaryKey>N</isPrimaryKey>
				<identity>N</identity>
				<inputType>textbox</inputType>
				<fieldDesc></fieldDesc>
				<refLookup></refLookup>
				<rows></rows>
				<cols></cols>
			</field>
			<field>
				<fieldName>tDataCat</fieldName>
				<fieldLabel>預設分網</fieldLabel>
				<dataType>char</dataType>
				<dataLen>1</dataLen>
				<inputLen>1</inputLen>
				<canNull>Y</canNull>
				<isPrimaryKey>N</isPrimaryKey>
				<identity>N</identity>
				<inputType>refSelect</inputType>
				<fieldDesc></fieldDesc>
				<refLookup>topDataCat</refLookup>
				<rows></rows>
				<cols></cols>
			</field>
		</fieldList>
	</dsTable>
</DataSchemaDef>
